README.rst
setup.py
aberdeen/__init__.py
aberdeen.egg-info/PKG-INFO
aberdeen.egg-info/SOURCES.txt
aberdeen.egg-info/dependency_links.txt
aberdeen.egg-info/requires.txt
aberdeen.egg-info/top_level.txt
aberdeen/git_hooks/update
aberdeen/utils/error_messages.py
aberdeen/utils/prompt.py
scripts/aberdeen-init
scripts/aberdeen-update-hook