Metadata-Version: 1.1
Name: aberdeen
Version: 0.4.0
Summary: Conversion from markdown files to database entries to use as the backend of a blog
Home-page: https://github.com/akubera/aberdeen
Author: Andrew Kubera
Author-email: andrew.kubera@gmail.com
License: Apache 2.0
Download-URL: https://github.com/akubera/aberdeen/archive/v0.4.0.tar.gz
Keywords: markdown,blog,publishing,nosql,mongodb
Platform: any
Classifier: Development Status :: 2 - Pre-Alpha
Classifier: Programming Language :: Python :: 3
Classifier: Programming Language :: Python :: 3.4
Classifier: Topic :: Utilities
Classifier: Topic :: Internet :: WWW/HTTP :: Dynamic Content
Classifier: License :: OSI Approved :: Apache Software License
